pystoned/CNLS.py
pystoned/CNLSDDF.py
pystoned/CNLSG.py
pystoned/CNLSRDF.py
pystoned/CQER.py
pystoned/CQERDDF.py
pystoned/CQERG.py
pystoned/CSVR.py
pystoned/DEA.py
pystoned/FDH.py
pystoned/ICNLS.py
pystoned/ICQER.py
pystoned/StoNED.py
pystoned/__init__.py
pystoned/constant.py
pystoned/dataset.py
pystoned/pCNLS.py
pystoned/pCQER.py
pystoned/pICQER.py
pystoned/plot.py
pystoned/pwCNLS.py
pystoned/pwCQER.py
pystoned/sCQER.py
pystoned/wCNLS.py
pystoned/wCQER.py
pystoned/weakCNLS.py
pystoned/data/41Firm.csv
pystoned/data/abatementCost.csv
pystoned/data/electricityFirms.csv
pystoned/data/riceProduction.csv
pystoned/utils/CNLSG1.py
pystoned/utils/CNLSG2.py
pystoned/utils/CNLSZG1.py
pystoned/utils/CNLSZG2.py
pystoned/utils/CQERG1.py
pystoned/utils/CQERG2.py
pystoned/utils/CQERZG1.py
pystoned/utils/CQERZG2.py
pystoned/utils/__init__.py
pystoned/utils/interpolation.py
pystoned/utils/sweet.py
pystoned/utils/tools.py
pystoned/utils/unihyper.py
pystoned-0.7.5.dist-info/LICENSE
pystoned-0.7.5.dist-info/METADATA
pystoned-0.7.5.dist-info/WHEEL
pystoned-0.7.5.dist-info/top_level.txt
pystoned-0.7.5.dist-info/RECORD
