Metadata-Version: 2.2
Name: pystoned
Version: 0.7.5
Summary: A Python Package for Convex Regression and Frontier Estimation
Home-page: https://github.com/ds2010/pyStoNED
Download-URL: https://pypi.org/project/pystoned/
Author: Sheng Dai, Yu-Hsueh Fang, Chia-Yen Lee, Timo Kuosmanen
Author-email: sheng.dai@zuel.edu.cn
License: GPLv3
Keywords: StoNED,CNLS,CER,CQR,Z-variables,CNLSG
Classifier: Development Status :: 5 - Production/Stable
Classifier: Intended Audience :: Science/Research
Classifier: Programming Language :: Python :: 3
Classifier: License :: OSI Approved :: GNU General Public License v3 (GPLv3)
Classifier: Operating System :: OS Independent
License-File: LICENSE
Requires-Dist: pyomo>=6.8.0
Requires-Dist: pandas>=1.1.3
Requires-Dist: numpy>=1.19.2
Requires-Dist: scipy>=1.5.2
Requires-Dist: matplotlib>=3.5.1
Requires-Dist: mosek>=10.1.13
Requires-Dist: openpyxl>=3.1.2
Dynamic: author
Dynamic: author-email
Dynamic: classifier
Dynamic: description
Dynamic: description-content-type
Dynamic: download-url
Dynamic: home-page
Dynamic: keywords
Dynamic: license
Dynamic: requires-dist
Dynamic: summary
